Elecpy/Backup.py
Elecpy/Calculation.py
Elecpy/Default.py
Elecpy/Diagram.py
Elecpy/File.py
Elecpy/Formula.py
Elecpy/GUIElements.py
Elecpy/Graph.py
Elecpy/Platform.py
Elecpy/Templates.py
Elecpy/Test.py
Elecpy/Tools.py
Elecpy/__init__.py
Elecpy-0.1.1.dist-info/METADATA
Elecpy-0.1.1.dist-info/WHEEL
Elecpy-0.1.1.dist-info/top_level.txt
Elecpy-0.1.1.dist-info/RECORD
